makedeb_srcinfo-0.8.1.dist-info/METADATA
makedeb_srcinfo-0.8.1.dist-info/WHEEL
makedeb_srcinfo-0.8.1.dist-info/license_files/LICENSE
makedeb_srcinfo/__init__.py
makedeb_srcinfo/makedeb_srcinfo.cpython-37m-x86_64-linux-gnu.so
makedeb_srcinfo-0.8.1.dist-info/RECORD
