Metadata-Version: 2.1
Name: makedeb-srcinfo
Version: 0.8.1
Classifier: Programming Language :: Rust
Classifier: Programming Language :: Python :: Implementation :: CPython
Classifier: Programming Language :: Python :: Implementation :: PyPy
License-File: LICENSE
Summary: Rust + Python library for parsing makedeb-styled .SRCINFO files
Keywords: makedeb,mpr,srcinfo,pkgbuild
Home-Page: https://github.com/makedeb/makedeb-srcinfo
Author: Hunter Wittenborn <hunter@hunterwittenborn.com>
Author-email: Hunter Wittenborn <hunter@hunterwittenborn.com>
License: GPL-3.0-or-later
Requires-Python: >=3.7
Project-URL: Source Code, https://github.com/makedeb/makedeb-srcinfo
